watdarepo
