Metadata-Version: 1.1
Name: watdarepo
Version: 0.2.0
Summary: Determines type and host of a repo.
Home-page: https://github.com/pydanny/watdarepo
Author: Daniel Greenfeld
Author-email: pydanny@gmail.com
License: BSD
Keywords: watdarepo,git,hg,mercurial,svn,bzr
Platform: UNKNOWN
Classifier: Development Status :: 3 - Alpha
Classifier: Intended Audience :: Developers
Classifier: License :: OSI Approved :: BSD License
Classifier: Operating System :: OS Independent
Classifier: Natural Language :: English
Classifier: Programming Language :: Python :: 2
Classifier: Programming Language :: Python :: 2.6
Classifier: Programming Language :: Python :: 2.7
Classifier: Programming Language :: Python :: 3
Classifier: Programming Language :: Python :: 3.3
Classifier: Topic :: Software Development :: Version Control
Classifier: Topic :: Utilities
